Workbook

Sheet 销货确认书
A1: 销 货 确 认 书
A2: SALES CONFIRMATION
A3: 卖 方 : | C3: 山东铭盛机械集团有限公司 | H3: NO.: | I3: 8278029-43-I-1
A4: SELLERS : | C4: SHANDONG MING SHENG MACHINERY GROUP CO., LTD | H4: DATE: | I4: 2026/08/20
A5: 地 址 : | C5: 山东省济宁市任城区仙营街道建设北路高鸿智汇大厦1722室 | H5: SIGNED AT: | I5: 2026/08/20
A6: Address: | C6: No. 68 Tongji Road, High-tech Development Zone, Jining City, Shandong Province
A11: 买 方 ： | B11: BUYERS: | C11: DAVID JOHN GIRLING | H11: TEL： | I11: 0061 412803303
A12: 地 址 ： | B12: ADDRESS: | C12: 133 Cedar Ave, Esk QLD 4312 AUS | H12: Email: | I12: julemark13@gmail.com
A15: 兹经买卖双方同意按下列条款成交:
A16: The undersigned Sellers and Buyers have agreed to choose the following transactions according to the
A17: terms and Conditions stipulated below:
A18: 1. 货号 | C18: 品名及规格 | F18: 数 量 | H18: 单 价 | I18: 金 额
A19: Art No. | C19: Description | F19: Quantity | H19: Unit Price | I19: Amount
A20: N/M | C20: Product Name 品名 | D20: Model 型号 | H20: FOB QingDao | I20: USD
C21: Forklift truck | D21: MS-35 | F21: 3 | G21: units | H21: 4852.63 | I21: =H21*F21 -> 14557.89
C22: Bucket attachment | D22: No model specified | F22: 3 | G22: units | H22: 260 | I22: =H22*F22 -> 780
C23: Forklift wheels | D23: Brand and model not specified | F23: 4 | G23: pieces | H23: 60 | I23: =H23*F23 -> 240
H24: TOTAL: | I24: =SUM(I21:I23) -> 15577.89
A25: 3.包 装: | B25: Packing: | C25: Unpackaged / Naked packaging
A26: 4.装 运 期: | B26: Time of Shipment: On or before: | E26: 前
A27: 5.装运口岸和目的地:Loading port & Destination：From | E27: QINGDAO | F27: CHINA To | G27: Brisbane AUSTRALIA
A28: 6.保 险:由买方按发票全部金额110%投保至 为止的 险。
A29: Insurance. To be affected by Sellers for 110% of full invoice value covering up to only.
A30: 7.付款条件: | B30: T/T
A31: 8.装船标记: | B31: N/M
A32: Shipping mark:
A33: 9.产 地: | B33: 中 国
A34: The place of origin or production: | D34: CHINA
A35: 10.备 注: | B35: Remarks:
A38: 买 方: | B38: BUYERS: | G38: 卖 方: | H38: SELLERS:

Sheet 发票
A1: 山东铭盛机械集团有限公司 SHANDONG MING SHENG MACHINERY GROUP CO., LTD 山东省济宁市任城区仙营街道建设北路高鸿智汇大厦1722室 No. 68 Tongji Road, High-tech Development Zone, Jining City, Shandong Province
A7: 商 业 发 票
A8: COMMERCIAL INVOICE
F9: 发 票 号 码 INVOICE NO. | G9: 8278029-43-I-1
F10: 合 同 号 码 CONTRACT NO. | G10: 2026/08/20
F11: 日 期 DATE | G11: 46254
A13: To： | B13: =销货确认书!C11 -> DAVID JOHN GIRLING | C13: 133 Cedar Ave, Esk QLD 4312 AUS
A15: Mark & Nos | B15: DESCRIPTION | D15: QUANTITY | F15: Unit Price | G15: Amount
B16: 品名 | C16: 型号 | F16: =销货确认书!G20 -> 0 | G16: RMB
A17: =销货确认书!A20 -> N/M | B17: =销货确认书!C21 -> Forklift truck | C17: =销货确认书!D21 -> MS-35 | D17: =销货确认书!F21 -> 3 | E17: =销货确认书!G21 -> units | F17: =销货确认书!H21 -> 4852.63 | G17: =销货确认书!I21 -> 14557.89
B18: =销货确认书!C22 -> Bucket attachment | C18: =销货确认书!D22 -> No model specified | D18: =销货确认书!F22 -> 3 | E18: =销货确认书!G22 -> units | F18: =销货确认书!H22 -> 260 | G18: =销货确认书!I22 -> 780
B19: =销货确认书!C23 -> Forklift wheels | C19: =销货确认书!D23 -> Brand and model not specified | D19: =销货确认书!F23 -> 4 | E19: =销货确认书!G23 -> pieces | F19: =销货确认书!H23 -> 60 | G19: =销货确认书!I23 -> 240
B20: TOTAL: | G20: =销货确认书!I24 -> 15577.89

Sheet 装箱清单
A1: 山东铭盛机械集团有限公司 SHANDONG MING SHENG MACHINERY GROUP CO., LTD 山东省济宁市任城区仙营街道建设北路高鸿智汇大厦1722室 No. 68 Tongji Road, High-tech Development Zone, Jining City, Shandong Province
A6: 装 箱 清 单
A7: PACKING LIST
H9: 合 同 号 码 CONTRACT NO.： | J9: 8278029-43-I-1
H10: 日 期 DATE： | J10: 46254
A13: To： | B13: DAVID JOHN GIRLING 133 Cedar Ave, EskQLD 4312 AUS
A16: 唛头 | B16: Product Name | C16: Model/Specification | D16: QUANTITY | H16: NET WEIGHT(KGS) | I16: GROSS WEIGHT(KGS) | J16: Volume | K16: Picture
A17: Mark & Nos | B17: DESCRIPTION | D17: QUANTITY | H17: N.W. | I17: G.W. | J17: CBM
A18: N/M | B18: =销货确认书!C21 -> Forklift truck | C18: MS-35 | D18: 3 | F18: units | H18: 12950KGS | I18: 12950KGS | J18: 50.74
B19: Bucket attachment | C19: No model specified | D19: 3 | F19: units | H19: 1080KG | I19: 1080KG | J19: 4.25
B20: Forklift wheels | C20: Brand and model not specified | D20: 4 | F20: pieces | H20: 260KG | I20: 260KG | J20: 1.01
A21: TOTAL: | D21: =SUM(D18:E20) -> 10 | H21: 14290KGS | J21: 56.00CBM | L21: 11090 | M21: 9997
A23: Packaging method: Unpackaged / Naked packaging
